{
    "name_eng": "Aghul",
    "uppercase_alphabet": [
        {
            "id": "idS3XEG41CUMICC1OT1A5M6E2R6G6O8X5J",
            "sign": "А",
            "unicodes": [
                "0410"
            ],
            "types": [],
            "description": "0410",
            "alts": []
        },
        {
            "id": "idIV9SG7JR54JWD1JXD52T1L31H8SCX1S4",
            "sign": "Б",
            "unicodes": [
                "0411"
            ],
            "types": [],
            "description": "0411",
            "alts": []
        },
        {
            "id": "idRCXDSPIIWR6B6IJ5TAHM9D7XWMNBVHDW",
            "sign": "В",
            "unicodes": [
                "0412"
            ],
            "types": [],
            "description": "0412",
            "alts": []
        },
        {
            "id": "id16C77N65RYLTR34TF0ANKQ9Z6ZF3N17L",
            "sign": "Г",
            "unicodes": [
                "0413"
            ],
            "types": [],
            "description": "0413",
            "alts": []
        },
        {
            "id": "id4TLPKTSLQG0F5TJFZUJ7WM5396NSB1TY",
            "sign": "Гь",
            "unicodes": [
                "0413",
                "044C"
            ],
            "types": [],
            "description": "0413, 044C",
            "alts": []
        },
        {
            "id": "idGSDX2AN2J1G86FX4KLLVRU87ETYYBBDL",
            "sign": "Гъ",
            "unicodes": [
                "0413",
                "044A"
            ],
            "types": [],
            "description": "0413, 044A",
            "alts": []
        },
        {
            "id": "idITVCYTNVFMTVE83N23KCIPU78LSJM249",
            "sign": "ГӀ",
            "unicodes": [
                "0413",
                "04C0"
            ],
            "types": [],
            "description": "0413, 04C0",
            "alts": []
        },
        {
            "id": "id5PMILXXHB8LNDOWHQOE5XTXQP4M6KDAW",
            "sign": "Д",
            "unicodes": [
                "0414"
            ],
            "types": [],
            "description": "0414",
            "alts": []
        },
        {
            "id": "idW9S1QBZTIFEZVEXOI5ISW5X8MW5UY8HR",
            "sign": "Дж",
            "unicodes": [
                "0414",
                "0436"
            ],
            "types": [],
            "description": "0414, 0436",
            "alts": []
        },
        {
            "id": "id6Y0GA6IRIXTTZNXMF9K30HX06KQUL0NY",
            "sign": "Е",
            "unicodes": [
                "0415"
            ],
            "types": [],
            "description": "0415",
            "alts": []
        },
        {
            "id": "idU9EXTO7L7SI1E0597R06U4Y1608DFS8Z",
            "sign": "Ё",
            "unicodes": [
                "0401"
            ],
            "types": [],
            "description": "0401",
            "alts": []
        },
        {
            "id": "idU2NGQ2DPOW2OHXWWMT0BH1N6NYOQFWT9",
            "sign": "Ж",
            "unicodes": [
                "0416"
            ],
            "types": [],
            "description": "0416",
            "alts": []
        },
        {
            "id": "idWZDRLEKCT2Y7DTI4WOW0GQHF0KWG3RV2",
            "sign": "З",
            "unicodes": [
                "0417"
            ],
            "types": [],
            "description": "0417",
            "alts": []
        },
        {
            "id": "idD3SZUQU0E7L5ZVA0GLP4HZG4E3X91ADQ",
            "sign": "И",
            "unicodes": [
                "0418"
            ],
            "types": [],
            "description": "0418",
            "alts": []
        },
        {
            "id": "idOI6UB30GQAWX4C4OIF2JOZCPHR38XWR6",
            "sign": "Й",
            "unicodes": [
                "0419"
            ],
            "types": [],
            "description": "0419",
            "alts": []
        },
        {
            "id": "idK3K8H6OH0TXHO6E0X43S7688T0WBG1CA",
            "sign": "К",
            "unicodes": [
                "041A"
            ],
            "types": [],
            "description": "041A",
            "alts": []
        },
        {
            "id": "idN4MMU9DWQA9YRFVVLK5NI6MVBR4R62BM",
            "sign": "Кь",
            "unicodes": [
                "041A",
                "044C"
            ],
            "types": [],
            "description": "041A, 044C",
            "alts": []
        },
        {
            "id": "idS82KH5S9VK1I9Q44IDEJ3D998RMEK6AE",
            "sign": "Кк",
            "unicodes": [
                "041A",
                "043A"
            ],
            "types": [],
            "description": "041A, 043A",
            "alts": []
        },
        {
            "id": "idPDHAB7H3PICA1I8IW4D2FEH7Z48TVVYW",
            "sign": "Къ",
            "unicodes": [
                "041A",
                "044A"
            ],
            "types": [],
            "description": "041A, 044A",
            "alts": []
        },
        {
            "id": "idRMKQ007U2VTINJQY1XTT6XAJTOFQ45BP",
            "sign": "КӀ",
            "unicodes": [
                "041A",
                "04C0"
            ],
            "types": [],
            "description": "041A, 04C0",
            "alts": []
        },
        {
            "id": "idSKPPP78M2D2UUTQCRVA7CKLD1QFHMZH2",
            "sign": "Л",
            "unicodes": [
                "041B"
            ],
            "types": [],
            "description": "041B",
            "alts": []
        },
        {
            "id": "id2G6BQWQUULFFZ3X9OIFZHSNE5NAFEKK1",
            "sign": "М",
            "unicodes": [
                "041C"
            ],
            "types": [],
            "description": "041C",
            "alts": []
        },
        {
            "id": "idZHS19TVJXC1Y8S8KODTXDKLYG80PDDEV",
            "sign": "Н",
            "unicodes": [
                "041D"
            ],
            "types": [],
            "description": "041D",
            "alts": []
        },
        {
            "id": "id0M23NVNOMJW6RCW2D9RO9T8EWY7SFU60",
            "sign": "О",
            "unicodes": [
                "041E"
            ],
            "types": [],
            "description": "041E",
            "alts": []
        },
        {
            "id": "idK4Y0X78KV16SCUC97NH8U801O5ULXWNX",
            "sign": "П",
            "unicodes": [
                "041F"
            ],
            "types": [],
            "description": "041F",
            "alts": []
        },
        {
            "id": "idZWPWRKG2XONYIV1W953EDH5T9D88OI3V",
            "sign": "Пп",
            "unicodes": [
                "041F",
                "043F"
            ],
            "types": [],
            "description": "041F, 043F",
            "alts": []
        },
        {
            "id": "idI2H0N0618ZJTV5D5ZRHMPQN9HEJRDJ3R",
            "sign": "ПӀ",
            "unicodes": [
                "041F",
                "04C0"
            ],
            "types": [],
            "description": "041F, 04C0",
            "alts": []
        },
        {
            "id": "idFAXP0SQCQDUYZ5PFSCHQWMQ0V0NFS98L",
            "sign": "Р",
            "unicodes": [
                "0420"
            ],
            "types": [],
            "description": "0420",
            "alts": []
        },
        {
            "id": "id2XPACUWOLXCSJEFYP4NZFD0LXA7H6BS3",
            "sign": "С",
            "unicodes": [
                "0421"
            ],
            "types": [],
            "description": "0421",
            "alts": []
        },
        {
            "id": "idSGL0MZAXILEJUMU76JXUZETNPNLZHCIP",
            "sign": "Т",
            "unicodes": [
                "0422"
            ],
            "types": [],
            "description": "0422",
            "alts": []
        },
        {
            "id": "idUSHUZ8TJJLMIEB2LLKV6YZJSVQ44HS1L",
            "sign": "Тт",
            "unicodes": [
                "0422",
                "0442"
            ],
            "types": [],
            "description": "0422, 0442",
            "alts": []
        },
        {
            "id": "idW4BFILY8X15MK6NZY27XGD4AWSJ9QYKV",
            "sign": "ТӀ",
            "unicodes": [
                "0422",
                "04C0"
            ],
            "types": [],
            "description": "0422, 04C0",
            "alts": []
        },
        {
            "id": "id6QHQA0ZMH4QP1HXNDLCP4Y5AEW5CS4MB",
            "sign": "У",
            "unicodes": [
                "0423"
            ],
            "types": [],
            "description": "0423",
            "alts": []
        },
        {
            "id": "idD1NRRG1TVMY4OWQCYCDWK85EXSX1IT37",
            "sign": "Уь",
            "unicodes": [
                "0423",
                "044C"
            ],
            "types": [],
            "description": "0423, 044C",
            "alts": []
        },
        {
            "id": "id5KTM8W3VODXJLQSIPS8YW2Q9F81FX402",
            "sign": "Ф",
            "unicodes": [
                "0424"
            ],
            "types": [],
            "description": "0424",
            "alts": []
        },
        {
            "id": "id9MUG066A4TLKLI4PARC4HYT5X71ABV12",
            "sign": "Х",
            "unicodes": [
                "0425"
            ],
            "types": [],
            "description": "0425",
            "alts": []
        },
        {
            "id": "idLYCGHZ36L39RPE5QA29VAYFKJEB45AFE",
            "sign": "Хь",
            "unicodes": [
                "0425",
                "044C"
            ],
            "types": [],
            "description": "0425, 044C",
            "alts": []
        },
        {
            "id": "idHGNU2LBC5MVKQZ10J1GDHOETCT38VGB1",
            "sign": "Хъ",
            "unicodes": [
                "0425",
                "044A"
            ],
            "types": [],
            "description": "0425, 044A",
            "alts": []
        },
        {
            "id": "idLFY3MEY8WVO9FQ2QREOSBEXAXMP7KDLJ",
            "sign": "ХӀ",
            "unicodes": [
                "0425",
                "04C0"
            ],
            "types": [],
            "description": "0425, 04C0",
            "alts": []
        },
        {
            "id": "id7TVQBNWWXY2YBXM9OHUIEXIY3MAMLB80",
            "sign": "Ц",
            "unicodes": [
                "0426"
            ],
            "types": [],
            "description": "0426",
            "alts": []
        },
        {
            "id": "idATETFPPKAH5DMN8SFWHTEENNAUP5R7TX",
            "sign": "ЦӀ",
            "unicodes": [
                "0426",
                "04C0"
            ],
            "types": [],
            "description": "0426, 04C0",
            "alts": []
        },
        {
            "id": "idG75VWGZJ4Y41OX4UK6TVKM7D8XMM5AED",
            "sign": "Ч",
            "unicodes": [
                "0427"
            ],
            "types": [],
            "description": "0427",
            "alts": []
        },
        {
            "id": "idXH30PH71LK1GTSFF127R1Z211WUY0B9O",
            "sign": "Чч",
            "unicodes": [
                "0427",
                "0447"
            ],
            "types": [],
            "description": "0427, 0447",
            "alts": []
        },
        {
            "id": "idNX3LEM57ISVTSGQ7PC45QDBED45WCNR0",
            "sign": "ЧӀ",
            "unicodes": [
                "0427",
                "04C0"
            ],
            "types": [],
            "description": "0427, 04C0",
            "alts": []
        },
        {
            "id": "idNFHTJ1EOSXOSEY9I7B7I5J1LK5DWS7AN",
            "sign": "Ш",
            "unicodes": [
                "0428"
            ],
            "types": [],
            "description": "0428",
            "alts": []
        },
        {
            "id": "idF4N5PEVLL02793W7I7BW4UDFOKS9NEOP",
            "sign": "Щ",
            "unicodes": [
                "0429"
            ],
            "types": [],
            "description": "0429",
            "alts": []
        },
        {
            "id": "idY0E2M54WLBAQBGVDVUWFTN5E4DNQHLY9",
            "sign": "Ъ",
            "unicodes": [
                "042A"
            ],
            "types": [],
            "description": "042A",
            "alts": []
        },
        {
            "id": "idE6QAVLD23S8M867KVI7AJ1F5E2VZL8Q7",
            "sign": "Ӏ",
            "unicodes": [
                "04C0"
            ],
            "types": [],
            "description": "04C0",
            "alts": []
        },
        {
            "id": "idN2LUZ2FKPBQ849TOQRE67T503R74E9IG",
            "sign": "Ы",
            "unicodes": [
                "042B"
            ],
            "types": [],
            "description": "042B",
            "alts": []
        },
        {
            "id": "idS6XPTL24Y9UII3D8FW2C8UTAWR0Y75GH",
            "sign": "Ь",
            "unicodes": [
                "042C"
            ],
            "types": [],
            "description": "042C",
            "alts": []
        },
        {
            "id": "id4X5CIHTXMT7R2L5MP4LJP0JUETNPU0CA",
            "sign": "Э",
            "unicodes": [
                "042D"
            ],
            "types": [],
            "description": "042D",
            "alts": []
        },
        {
            "id": "idYZ7QBM6UN3OF9VHJWIRQEJGRSGWM4CEN",
            "sign": "Ю",
            "unicodes": [
                "042E"
            ],
            "types": [],
            "description": "042E",
            "alts": []
        },
        {
            "id": "id9NBWOOWGRSIA0KMADDW2BWJG5W88D95A",
            "sign": "Я",
            "unicodes": [
                "042F"
            ],
            "types": [],
            "description": "042F",
            "alts": []
        }
    ],
    "lowercase_alphabet": [
        {
            "id": "idKUBENY08NOZUL7V2LBI9EUJ9P9UBXW64",
            "sign": "а",
            "unicodes": [
                "0430"
            ],
            "types": [],
            "description": "0430",
            "alts": []
        },
        {
            "id": "idYMXF9C5W8K1MR30VL63ZN7FI0B5GYM1G",
            "sign": "б",
            "unicodes": [
                "0431"
            ],
            "types": [],
            "description": "0431",
            "alts": []
        },
        {
            "id": "idJC3WQI3ABEZWXHTS6EE0WZERHEJCM575",
            "sign": "в",
            "unicodes": [
                "0432"
            ],
            "types": [],
            "description": "0432",
            "alts": []
        },
        {
            "id": "id3EIN7M66EPPL6LMVUQS7AX9RNDDTA4FQ",
            "sign": "г",
            "unicodes": [
                "0433"
            ],
            "types": [],
            "description": "0433",
            "alts": []
        },
        {
            "id": "idNX1X9XG3CV6RF5UW3N6Y1YG6IQBH1P4G",
            "sign": "гъ",
            "unicodes": [
                "0433",
                "044A"
            ],
            "types": [],
            "description": "0433, 044A",
            "alts": []
        },
        {
            "id": "idVPOEZ6K5M2E6Y3JN5TPL0KTJZE9U3198",
            "sign": "гь",
            "unicodes": [
                "0433",
                "044C"
            ],
            "types": [],
            "description": "0433, 044C",
            "alts": []
        },
        {
            "id": "id3GS65KCLF3LSUGZKSVKHM0KPVSLSOGED",
            "sign": "гӏ",
            "unicodes": [
                "0433",
                "04CF"
            ],
            "types": [],
            "description": "0433, 04CF",
            "alts": []
        },
        {
            "id": "id4NYH79IEN1088OY8EP1ZPG6URLQVB5XM",
            "sign": "д",
            "unicodes": [
                "0434"
            ],
            "types": [],
            "description": "0434",
            "alts": []
        },
        {
            "id": "idREBHWUSY66Y3QBJFNAB1WURERRS5FZUO",
            "sign": "дж",
            "unicodes": [
                "0434",
                "0436"
            ],
            "types": [],
            "description": "0434, 0436",
            "alts": []
        },
        {
            "id": "idTG05UT02FJSCLFKGEKFYTK24LQ998WM6",
            "sign": "е",
            "unicodes": [
                "0435"
            ],
            "types": [],
            "description": "0435",
            "alts": []
        },
        {
            "id": "idH4ADXVRL0SEFEQRETSEV4HVDG0HU0BQS",
            "sign": "ё",
            "unicodes": [
                "0451"
            ],
            "types": [],
            "description": "0451",
            "alts": []
        },
        {
            "id": "id6E93NP9E9KTMTDYMM7Z2C42ZT9CUZPHK",
            "sign": "ж",
            "unicodes": [
                "0436"
            ],
            "types": [],
            "description": "0436",
            "alts": []
        },
        {
            "id": "id1I7A4EDX5PCI55YGCSVDWHTQFQVV39CI",
            "sign": "з",
            "unicodes": [
                "0437"
            ],
            "types": [],
            "description": "0437",
            "alts": []
        },
        {
            "id": "idHCJRQ8W91COBBQMTQM4SOKABRDA653DD",
            "sign": "и",
            "unicodes": [
                "0438"
            ],
            "types": [],
            "description": "0438",
            "alts": []
        },
        {
            "id": "idNW442VBGFRQBCQLQDQWJ6DM189FYJBSB",
            "sign": "й",
            "unicodes": [
                "0439"
            ],
            "types": [],
            "description": "0439",
            "alts": []
        },
        {
            "id": "idJMZ93AZC2L0J3SNLCMSRPR1IOHSZVZTA",
            "sign": "к",
            "unicodes": [
                "043A"
            ],
            "types": [],
            "description": "043A",
            "alts": []
        },
        {
            "id": "idP0FUFPTVYYIZALYHQDUFR4K1FYL3H0GT",
            "sign": "кь",
            "unicodes": [
                "043A",
                "044C"
            ],
            "types": [],
            "description": "043A, 044C",
            "alts": []
        },
        {
            "id": "idAUE6H41D8NF9U6EZSE3LHDJNTUI51A2T",
            "sign": "кк",
            "unicodes": [
                "043A",
                "043A"
            ],
            "types": [],
            "description": "043A, 043A",
            "alts": []
        },
        {
            "id": "idXA9OKUA4EB9M3IXDMZHEI32GIMQJ8FZJ",
            "sign": "къ",
            "unicodes": [
                "043A",
                "044A"
            ],
            "types": [],
            "description": "043A, 044A",
            "alts": []
        },
        {
            "id": "idRHDXOAHF9DDK4AZ5FYPVTXCSOYHRA8Y2",
            "sign": "кӏ",
            "unicodes": [
                "043A",
                "04CF"
            ],
            "types": [],
            "description": "043A, 04CF",
            "alts": []
        },
        {
            "id": "idWZXEH80BXYEM8LCE3KGV9A63O6Y6HRSG",
            "sign": "л",
            "unicodes": [
                "043B"
            ],
            "types": [],
            "description": "043B",
            "alts": []
        },
        {
            "id": "id46EN21AD0YP2HVJGWBXOMPUQL9LRERNG",
            "sign": "м",
            "unicodes": [
                "043C"
            ],
            "types": [],
            "description": "043C",
            "alts": []
        },
        {
            "id": "idZUJWFIPKMU864L8FHJEJAI5LVE7DITMS",
            "sign": "н",
            "unicodes": [
                "043D"
            ],
            "types": [],
            "description": "043D",
            "alts": []
        },
        {
            "id": "idLG3E5AGDR4WSUT1EF7WQIQDVRVZFHA62",
            "sign": "о",
            "unicodes": [
                "043E"
            ],
            "types": [],
            "description": "043E",
            "alts": []
        },
        {
            "id": "idZ7EO3HH8K4CNZ8Q41FOZA1BEHWP5SJYQ",
            "sign": "п",
            "unicodes": [
                "043F"
            ],
            "types": [],
            "description": "043F",
            "alts": []
        },
        {
            "id": "idG5VB2SUF3JYJP9LU5KNN5Z1SNUQGCEBS",
            "sign": "пп",
            "unicodes": [
                "043F",
                "043F"
            ],
            "types": [],
            "description": "043F, 043F",
            "alts": []
        },
        {
            "id": "idN508B9C985R9CTNIJA8ZYZFDPP9Q6CSD",
            "sign": "пӏ",
            "unicodes": [
                "043F",
                "04CF"
            ],
            "types": [],
            "description": "043F, 04CF",
            "alts": []
        },
        {
            "id": "idR6GGHDXL9UMLX6D3PEA4P07UE7YBI6DA",
            "sign": "р",
            "unicodes": [
                "0440"
            ],
            "types": [],
            "description": "0440",
            "alts": []
        },
        {
            "id": "id5PCUOHEGKHXD6JXJAHDG56LSTQJJIM0B",
            "sign": "с",
            "unicodes": [
                "0441"
            ],
            "types": [],
            "description": "0441",
            "alts": []
        },
        {
            "id": "idLYEU8TEJ112TKCVOMGK3HV31QMCDQIB1",
            "sign": "т",
            "unicodes": [
                "0442"
            ],
            "types": [],
            "description": "0442",
            "alts": []
        },
        {
            "id": "idWDZ6ATS9WAMY429OB7EXOPRAEMYUDQTJ",
            "sign": "тт",
            "unicodes": [
                "0442",
                "0442"
            ],
            "types": [],
            "description": "0442, 0442",
            "alts": []
        },
        {
            "id": "idLTFRCCEWKGKGUZ9FYEWIXP87D7A0J80G",
            "sign": "тӏ",
            "unicodes": [
                "0442",
                "04CF"
            ],
            "types": [],
            "description": "0442, 04CF",
            "alts": []
        },
        {
            "id": "idE0CXIV4HOJFQ4J0YMJJOTS209FN29KO9",
            "sign": "у",
            "unicodes": [
                "0443"
            ],
            "types": [],
            "description": "0443",
            "alts": []
        },
        {
            "id": "idTAKZ81NNP0IONBVK7WM5IZ3OSL501O4B",
            "sign": "уь",
            "unicodes": [
                "0443",
                "044C"
            ],
            "types": [],
            "description": "0443, 044C",
            "alts": []
        },
        {
            "id": "idQT4EUI6AMGWB3G1AS1SC86BAQPF4MSLW",
            "sign": "ф",
            "unicodes": [
                "0444"
            ],
            "types": [],
            "description": "0444",
            "alts": []
        },
        {
            "id": "idC3R0LOP9EBD4VLQQAB97CK6D7NKQXCE3",
            "sign": "х",
            "unicodes": [
                "0445"
            ],
            "types": [],
            "description": "0445",
            "alts": []
        },
        {
            "id": "idM0H2HR9A4V54Y4EE2Q7A5WZXX5AANX5X",
            "sign": "хь",
            "unicodes": [
                "0445",
                "044C"
            ],
            "types": [],
            "description": "0445, 044C",
            "alts": []
        },
        {
            "id": "id819TJE6RZOIM3CB85PYKG8VVKB8R5PTV",
            "sign": "хъ",
            "unicodes": [
                "0445",
                "044A"
            ],
            "types": [],
            "description": "0445, 044A",
            "alts": []
        },
        {
            "id": "idONT8WR2VALNQI5OMOCZSZMRQJIN2CO8G",
            "sign": "хӏ",
            "unicodes": [
                "0445",
                "04CF"
            ],
            "types": [],
            "description": "0445, 04CF",
            "alts": []
        },
        {
            "id": "idVCYNU1XSTTGHA2WAN36NK24CLG7QNWLN",
            "sign": "ц",
            "unicodes": [
                "0446"
            ],
            "types": [],
            "description": "0446",
            "alts": []
        },
        {
            "id": "idV26Q4K2WSGK92P806IH9AIH2PD1Z90TP",
            "sign": "цӏ",
            "unicodes": [
                "0446",
                "04CF"
            ],
            "types": [],
            "description": "0446, 04CF",
            "alts": []
        },
        {
            "id": "idCG0H1KMK8FRI5V0VD0PM60A216CL1PB8",
            "sign": "ч",
            "unicodes": [
                "0447"
            ],
            "types": [],
            "description": "0447",
            "alts": []
        },
        {
            "id": "idSDSJ9DWTXKHAXKLFKAZ0MIJWALBFOYEQ",
            "sign": "чч",
            "unicodes": [
                "0447",
                "0447"
            ],
            "types": [],
            "description": "0447, 0447",
            "alts": []
        },
        {
            "id": "id6ZR3Y0DYDBEJXSWB6RM5RA7AACZLL4QT",
            "sign": "чӏ",
            "unicodes": [
                "0447",
                "04CF"
            ],
            "types": [],
            "description": "0447, 04CF",
            "alts": []
        },
        {
            "id": "id3C0DOW2YSUDVIYAW9UGS2GTBU785DWHE",
            "sign": "ш",
            "unicodes": [
                "0448"
            ],
            "types": [],
            "description": "0448",
            "alts": []
        },
        {
            "id": "id3YR8GSN6VLXPX0E6VIBGXW4FTKBI0B7X",
            "sign": "щ",
            "unicodes": [
                "0449"
            ],
            "types": [],
            "description": "0449",
            "alts": []
        },
        {
            "id": "idF2HA81GROR2B9KQ0T9RKOOQN0JM4XKVY",
            "sign": "ъ",
            "unicodes": [
                "044A"
            ],
            "types": [],
            "description": "044A",
            "alts": []
        },
        {
            "id": "idWNQ25UV4GIWS1I7RUTEZBDOIPWVGOA5P",
            "sign": "ӏ",
            "unicodes": [
                "04CF"
            ],
            "types": [],
            "description": "04CF",
            "alts": []
        },
        {
            "id": "idXTH5B9RBM6FVKTXYDMKU3XO5ZFJAS0IN",
            "sign": "ы",
            "unicodes": [
                "044B"
            ],
            "types": [],
            "description": "044B",
            "alts": []
        },
        {
            "id": "idYQUJEH9E79KYXNJ8E24TB3502RL9RLFW",
            "sign": "ь",
            "unicodes": [
                "044C"
            ],
            "types": [],
            "description": "044C",
            "alts": []
        },
        {
            "id": "idY0I809S2S6IKR9TRNKCWJ3M514CMGNBK",
            "sign": "э",
            "unicodes": [
                "044D"
            ],
            "types": [],
            "description": "044D",
            "alts": []
        },
        {
            "id": "idP5XC3IR2PER3RS248XXAISHL78BHS7CR",
            "sign": "ю",
            "unicodes": [
                "044E"
            ],
            "types": [],
            "description": "044E",
            "alts": []
        },
        {
            "id": "idTUAIH24MH8BPXXZ2LM1R9EIGO37SFSDE",
            "sign": "я",
            "unicodes": [
                "044F"
            ],
            "types": [],
            "description": "044F",
            "alts": []
        }
    ],
    "uppercase_dialect": [],
    "lowercase_dialect": [],
    "uppercase_historic": [],
    "lowercase_historic": [],
    "uppercase_lexic": [],
    "lowercase_lexic": [],
    "uppercase_unicodes_list": [
        {
            "id": "id6NR5R8XB5W7MW7P3A6SKJYUO636R6J6G",
            "sign": "А",
            "unicode": "0410",
            "display_unicode": "0410",
            "types": [],
            "description": "CYRILLIC CAPITAL LETTER A"
        },
        {
            "id": "idPFYOW4ECAQIFC8BI0Q51ZDJT9FCADOFJ",
            "sign": "Б",
            "unicode": "0411",
            "display_unicode": "0411",
            "types": [],
            "description": "CYRILLIC CAPITAL LETTER BE"
        },
        {
            "id": "idELN7A84QVUXBR6BVL3LKY3CUVJ5U5ZAA",
            "sign": "В",
            "unicode": "0412",
            "display_unicode": "0412",
            "types": [],
            "description": "CYRILLIC CAPITAL LETTER VE"
        },
        {
            "id": "idEDIO9KDHJ4O3YN5M8679NFHHU2DSEWFF",
            "sign": "Г",
            "unicode": "0413",
            "display_unicode": "0413",
            "types": [],
            "description": "CYRILLIC CAPITAL LETTER GHE"
        },
        {
            "id": "idRU4GOZGTOKI3Y3XLDZ5S2B3WXM66LPS6",
            "sign": "Д",
            "unicode": "0414",
            "display_unicode": "0414",
            "types": [],
            "description": "CYRILLIC CAPITAL LETTER DE"
        },
        {
            "id": "idUMFUEWTM7FL87XZ8VHA4880KBBC8SXT5",
            "sign": "Е",
            "unicode": "0415",
            "display_unicode": "0415",
            "types": [],
            "description": "CYRILLIC CAPITAL LETTER IE"
        },
        {
            "id": "idYU1BTGV5QQ7EAF7E0HLUHBR04G5OTD0P",
            "sign": "Ё",
            "unicode": "0401",
            "display_unicode": "0401",
            "types": [],
            "description": "CYRILLIC CAPITAL LETTER IO"
        },
        {
            "id": "id1C8WMNLJYK59WUZMTOHRNAS865QO94SZ",
            "sign": "Ж",
            "unicode": "0416",
            "display_unicode": "0416",
            "types": [],
            "description": "CYRILLIC CAPITAL LETTER ZHE"
        },
        {
            "id": "idN04JBXRRPGIWWAX18E7DU50A2H9VZ9CB",
            "sign": "З",
            "unicode": "0417",
            "display_unicode": "0417",
            "types": [],
            "description": "CYRILLIC CAPITAL LETTER ZE"
        },
        {
            "id": "idAZET9LR2YP86F3JAUKSYE7EQ1FPWWPFL",
            "sign": "И",
            "unicode": "0418",
            "display_unicode": "0418",
            "types": [],
            "description": "CYRILLIC CAPITAL LETTER I"
        },
        {
            "id": "idE7IU7BWHEC0C98JMF242LHD7SL47H5QE",
            "sign": "Й",
            "unicode": "0419",
            "display_unicode": "0419",
            "types": [],
            "description": "CYRILLIC CAPITAL LETTER SHORT I"
        },
        {
            "id": "idFD47EX7C7131IRYLUPOQ0O96NRFBPLUX",
            "sign": "К",
            "unicode": "041A",
            "display_unicode": "041A",
            "types": [],
            "description": "CYRILLIC CAPITAL LETTER KA"
        },
        {
            "id": "id8T5PB7D0XWZ8DHRXTGO8MCZ72RGFDDR4",
            "sign": "Л",
            "unicode": "041B",
            "display_unicode": "041B",
            "types": [],
            "description": "CYRILLIC CAPITAL LETTER EL"
        },
        {
            "id": "idJ1ME5LZLCDQ1ECPHJUVVV18VKU3LFM5T",
            "sign": "М",
            "unicode": "041C",
            "display_unicode": "041C",
            "types": [],
            "description": "CYRILLIC CAPITAL LETTER EM"
        },
        {
            "id": "id955E1G0T0G2B1NFFJSOTVCPAHLXQY7YF",
            "sign": "Н",
            "unicode": "041D",
            "display_unicode": "041D",
            "types": [],
            "description": "CYRILLIC CAPITAL LETTER EN"
        },
        {
            "id": "idWRUY28AN22UNK8SZJ5VFZEGTK4CJU0SR",
            "sign": "О",
            "unicode": "041E",
            "display_unicode": "041E",
            "types": [],
            "description": "CYRILLIC CAPITAL LETTER O"
        },
        {
            "id": "idQI6OSM8PQHVJGFKTED2U4OP5JAG1RITO",
            "sign": "П",
            "unicode": "041F",
            "display_unicode": "041F",
            "types": [],
            "description": "CYRILLIC CAPITAL LETTER PE"
        },
        {
            "id": "id6FXIVXE62P965YKVCWCNN0UEEU7F9N3R",
            "sign": "Р",
            "unicode": "0420",
            "display_unicode": "0420",
            "types": [],
            "description": "CYRILLIC CAPITAL LETTER ER"
        },
        {
            "id": "idQJ98MPZ6BWFU6OYK119QXEG7FDE2R8XL",
            "sign": "С",
            "unicode": "0421",
            "display_unicode": "0421",
            "types": [],
            "description": "CYRILLIC CAPITAL LETTER ES"
        },
        {
            "id": "idXL2B66OEDBX3MUEO8CXTTMTFWX484L13",
            "sign": "Т",
            "unicode": "0422",
            "display_unicode": "0422",
            "types": [],
            "description": "CYRILLIC CAPITAL LETTER TE"
        },
        {
            "id": "idK3GLJJU5IO6SNI48MADLNFI4PAVS6JKE",
            "sign": "У",
            "unicode": "0423",
            "display_unicode": "0423",
            "types": [],
            "description": "CYRILLIC CAPITAL LETTER U"
        },
        {
            "id": "id3R8BT3507YEJ2D4V7IMEFQB3BNGFGAJS",
            "sign": "Ф",
            "unicode": "0424",
            "display_unicode": "0424",
            "types": [],
            "description": "CYRILLIC CAPITAL LETTER EF"
        },
        {
            "id": "idZI0M7Z1JRNWMVPPS1KBZEQ8ZI5RVKMJG",
            "sign": "Х",
            "unicode": "0425",
            "display_unicode": "0425",
            "types": [],
            "description": "CYRILLIC CAPITAL LETTER HA"
        },
        {
            "id": "idE4BP97GC2AZDR8PXQPFU1UX6KW7BAYKR",
            "sign": "Ц",
            "unicode": "0426",
            "display_unicode": "0426",
            "types": [],
            "description": "CYRILLIC CAPITAL LETTER TSE"
        },
        {
            "id": "idJNTITJVAJW9F6BAKNYWV94HPJA2RMWMT",
            "sign": "Ч",
            "unicode": "0427",
            "display_unicode": "0427",
            "types": [],
            "description": "CYRILLIC CAPITAL LETTER CHE"
        },
        {
            "id": "idW89IGZZOGLGNEDRU19278LDX4PNQ054O",
            "sign": "Ш",
            "unicode": "0428",
            "display_unicode": "0428",
            "types": [],
            "description": "CYRILLIC CAPITAL LETTER SHA"
        },
        {
            "id": "idY8554359HN7Y8E3BKPTO4X6YGNDY3F56",
            "sign": "Щ",
            "unicode": "0429",
            "display_unicode": "0429",
            "types": [],
            "description": "CYRILLIC CAPITAL LETTER SHCHA"
        },
        {
            "id": "idQX92RVEC4BWU5WAE40D6VPCKX8JHDOKO",
            "sign": "Ъ",
            "unicode": "042A",
            "display_unicode": "042A",
            "types": [],
            "description": "CYRILLIC CAPITAL LETTER HARD SIGN"
        },
        {
            "id": "idMYF3HDMFY6ICGMUCDQJ74PHASWBHN8DY",
            "sign": "Ӏ",
            "unicode": "04C0",
            "display_unicode": "04C0",
            "types": [],
            "description": "CYRILLIC LETTER PALOCHKA"
        },
        {
            "id": "idMKUNVQ332SOAHBPZOBX3IV9NLMOQNGVT",
            "sign": "Ы",
            "unicode": "042B",
            "display_unicode": "042B",
            "types": [],
            "description": "CYRILLIC CAPITAL LETTER YERU"
        },
        {
            "id": "idXXJJJPCGEDNBT3P4CHGJNMO1OVP0Q3CO",
            "sign": "Ь",
            "unicode": "042C",
            "display_unicode": "042C",
            "types": [],
            "description": "CYRILLIC CAPITAL LETTER SOFT SIGN"
        },
        {
            "id": "idU9ZMOS7SF95Q7D8LDAQE95ANRUTMEUAX",
            "sign": "Э",
            "unicode": "042D",
            "display_unicode": "042D",
            "types": [],
            "description": "CYRILLIC CAPITAL LETTER E"
        },
        {
            "id": "idWRT7SRUKX6X69D7XZZEPI2N9654VB7RP",
            "sign": "Ю",
            "unicode": "042E",
            "display_unicode": "042E",
            "types": [],
            "description": "CYRILLIC CAPITAL LETTER YU"
        },
        {
            "id": "id3ICIKYRALIWCSQZ3J85CZVDUEE5VABK3",
            "sign": "Я",
            "unicode": "042F",
            "display_unicode": "042F",
            "types": [],
            "description": "CYRILLIC CAPITAL LETTER YA"
        }
    ],
    "lowercase_unicodes_list": [
        {
            "id": "idFK4NJDV9RIUBCI67XM8LG9V09WG45ZPN",
            "sign": "а",
            "unicode": "0430",
            "display_unicode": "0430",
            "types": [],
            "description": "CYRILLIC SMALL LETTER A"
        },
        {
            "id": "idNFNWHI7Q9P0XL2DBWSRMEB8E1SH0YRDQ",
            "sign": "б",
            "unicode": "0431",
            "display_unicode": "0431",
            "types": [],
            "description": "CYRILLIC SMALL LETTER BE"
        },
        {
            "id": "idIWFNKXCWJIRD5RVHL4YHWB2FB7YB89VB",
            "sign": "в",
            "unicode": "0432",
            "display_unicode": "0432",
            "types": [],
            "description": "CYRILLIC SMALL LETTER VE"
        },
        {
            "id": "idD4VG93KX4L4NAEP7RC2ZWN626C22S96A",
            "sign": "г",
            "unicode": "0433",
            "display_unicode": "0433",
            "types": [],
            "description": "CYRILLIC SMALL LETTER GHE"
        },
        {
            "id": "idP35ZFJO98306H2DMUAG94D6OX9GSJ8HG",
            "sign": "д",
            "unicode": "0434",
            "display_unicode": "0434",
            "types": [],
            "description": "CYRILLIC SMALL LETTER DE"
        },
        {
            "id": "id11Q1W05GFUCGXIJBMCFGBR3VXEYUG6V3",
            "sign": "е",
            "unicode": "0435",
            "display_unicode": "0435",
            "types": [],
            "description": "CYRILLIC SMALL LETTER IE"
        },
        {
            "id": "idV2UYWK2RTNSCO8LMB9M9MYH7AVTP26QN",
            "sign": "ё",
            "unicode": "0451",
            "display_unicode": "0451",
            "types": [],
            "description": "CYRILLIC SMALL LETTER IO"
        },
        {
            "id": "idYV2S5179GSSY1FCEPAQM8JE9XI7QKBVM",
            "sign": "ж",
            "unicode": "0436",
            "display_unicode": "0436",
            "types": [],
            "description": "CYRILLIC SMALL LETTER ZHE"
        },
        {
            "id": "idJDCOFLL8N7NDFHZUB7H53NS8PQ371NV6",
            "sign": "з",
            "unicode": "0437",
            "display_unicode": "0437",
            "types": [],
            "description": "CYRILLIC SMALL LETTER ZE"
        },
        {
            "id": "idIB5AKDH35T86U6XVPFBLC1OOATYNM83P",
            "sign": "и",
            "unicode": "0438",
            "display_unicode": "0438",
            "types": [],
            "description": "CYRILLIC SMALL LETTER I"
        },
        {
            "id": "id91LFZNWPG66DWDY734KFHXYPOEGB7SYJ",
            "sign": "й",
            "unicode": "0439",
            "display_unicode": "0439",
            "types": [],
            "description": "CYRILLIC SMALL LETTER SHORT I"
        },
        {
            "id": "idMTMDGZRZPUN3APC7ZHF35F8NKVG89Y0Q",
            "sign": "к",
            "unicode": "043A",
            "display_unicode": "043A",
            "types": [],
            "description": "CYRILLIC SMALL LETTER KA"
        },
        {
            "id": "id8EMNF4PAP4CJ43UNI8LPCNC06FZPNELW",
            "sign": "л",
            "unicode": "043B",
            "display_unicode": "043B",
            "types": [],
            "description": "CYRILLIC SMALL LETTER EL"
        },
        {
            "id": "idN7F36Z3V00LPWR7OB3ATOD2T0AB9WSWD",
            "sign": "м",
            "unicode": "043C",
            "display_unicode": "043C",
            "types": [],
            "description": "CYRILLIC SMALL LETTER EM"
        },
        {
            "id": "idWGSHECBO3PCP07GL4NEBT13BCUJ2VD0K",
            "sign": "н",
            "unicode": "043D",
            "display_unicode": "043D",
            "types": [],
            "description": "CYRILLIC SMALL LETTER EN"
        },
        {
            "id": "idSFIT8TD01A8VZZ4G1PJZ2YSHB3UC81ZV",
            "sign": "о",
            "unicode": "043E",
            "display_unicode": "043E",
            "types": [],
            "description": "CYRILLIC SMALL LETTER O"
        },
        {
            "id": "idZDQ32HK5MHAMI1NRPCTSMN2Z6167H0FI",
            "sign": "п",
            "unicode": "043F",
            "display_unicode": "043F",
            "types": [],
            "description": "CYRILLIC SMALL LETTER PE"
        },
        {
            "id": "id0YAI8ESXPK62G6GHL5FGZS2O616JUS3O",
            "sign": "р",
            "unicode": "0440",
            "display_unicode": "0440",
            "types": [],
            "description": "CYRILLIC SMALL LETTER ER"
        },
        {
            "id": "idLGDV26EV072ZCV8H09V6SJG0WS0D8WJU",
            "sign": "с",
            "unicode": "0441",
            "display_unicode": "0441",
            "types": [],
            "description": "CYRILLIC SMALL LETTER ES"
        },
        {
            "id": "idE4FZ8PPOZNSUW3PIDVKIYNSSFOW82GC0",
            "sign": "т",
            "unicode": "0442",
            "display_unicode": "0442",
            "types": [],
            "description": "CYRILLIC SMALL LETTER TE"
        },
        {
            "id": "idOMWZ3R5DXB2BDIBEVV9KSRSAOKT2EVJQ",
            "sign": "у",
            "unicode": "0443",
            "display_unicode": "0443",
            "types": [],
            "description": "CYRILLIC SMALL LETTER U"
        },
        {
            "id": "idOSJCINT1YLRONFQWWNCSODDRA1SJVP72",
            "sign": "ф",
            "unicode": "0444",
            "display_unicode": "0444",
            "types": [],
            "description": "CYRILLIC SMALL LETTER EF"
        },
        {
            "id": "idD6OKRW0QAIYB84DKCFWGTD2H1I2GFRVQ",
            "sign": "х",
            "unicode": "0445",
            "display_unicode": "0445",
            "types": [],
            "description": "CYRILLIC SMALL LETTER HA"
        },
        {
            "id": "idIFMK5NEXLK453UECJHZW64ASR4LDWZRM",
            "sign": "ц",
            "unicode": "0446",
            "display_unicode": "0446",
            "types": [],
            "description": "CYRILLIC SMALL LETTER TSE"
        },
        {
            "id": "idTQI9DG5JNWXPZCK6HRK1UZDMRLF4AW92",
            "sign": "ч",
            "unicode": "0447",
            "display_unicode": "0447",
            "types": [],
            "description": "CYRILLIC SMALL LETTER CHE"
        },
        {
            "id": "idJ467WIJXMD9DN9N4GQLB58EYB8THD48K",
            "sign": "ш",
            "unicode": "0448",
            "display_unicode": "0448",
            "types": [],
            "description": "CYRILLIC SMALL LETTER SHA"
        },
        {
            "id": "idE4VXA5VNKHAL4UTS2BQC620RE0CI0ZDX",
            "sign": "щ",
            "unicode": "0449",
            "display_unicode": "0449",
            "types": [],
            "description": "CYRILLIC SMALL LETTER SHCHA"
        },
        {
            "id": "id7IGA4ZB2EAQP6T038XLCIXF8WLV0ABAS",
            "sign": "ъ",
            "unicode": "044A",
            "display_unicode": "044A",
            "types": [],
            "description": "CYRILLIC SMALL LETTER HARD SIGN"
        },
        {
            "id": "idBDPUDLH8ND6D9U5X18EPDJAZJT8HINP6",
            "sign": "ӏ",
            "unicode": "04CF",
            "display_unicode": "04CF",
            "types": [],
            "description": "CYRILLIC SMALL LETTER PALOCHKA"
        },
        {
            "id": "idEOV39OC4JERWRMXTA2OAMUU9R5YO6DOT",
            "sign": "ы",
            "unicode": "044B",
            "display_unicode": "044B",
            "types": [],
            "description": "CYRILLIC SMALL LETTER YERU"
        },
        {
            "id": "idF7JJL0489PXG6AILVWUMQIOO9I5QQUUY",
            "sign": "ь",
            "unicode": "044C",
            "display_unicode": "044C",
            "types": [],
            "description": "CYRILLIC SMALL LETTER SOFT SIGN"
        },
        {
            "id": "idBTQNUV5NTY7UU2136ZFJ735YGE0YFT32",
            "sign": "э",
            "unicode": "044D",
            "display_unicode": "044D",
            "types": [],
            "description": "CYRILLIC SMALL LETTER E"
        },
        {
            "id": "id4OIZEQ6YJS5XUTVZ07HLHRFPHPGWQU5A",
            "sign": "ю",
            "unicode": "044E",
            "display_unicode": "044E",
            "types": [],
            "description": "CYRILLIC SMALL LETTER YU"
        },
        {
            "id": "idT0FU97H42Q9HCHUTM4X0DJNMX8RK9AWM",
            "sign": "я",
            "unicode": "044F",
            "display_unicode": "044F",
            "types": [],
            "description": "CYRILLIC SMALL LETTER YA"
        }
    ]
}